cinderlib_csi/__init__.py
cinderlib_csi/cinderlib_csi.py
cinderlib_csi/csi_pb2.py
cinderlib_csi/csi_pb2_grpc.py
cinderlib_csi/csi_types.py
cinderlib_csi-0.0.2.dist-info/DESCRIPTION.rst
cinderlib_csi-0.0.2.dist-info/METADATA
cinderlib_csi-0.0.2.dist-info/RECORD
cinderlib_csi-0.0.2.dist-info/WHEEL
cinderlib_csi-0.0.2.dist-info/dependency_links.txt
cinderlib_csi-0.0.2.dist-info/entry_points.txt
cinderlib_csi-0.0.2.dist-info/metadata.json
cinderlib_csi-0.0.2.dist-info/top_level.txt
