Metadata-Version: 2.0
Name: cinderlib-csi
Version: 0.0.2
Summary: CSI driver supporting all Cinder drivers without needing to run any additional services like RabbitMQ, MariaDB, or Cinder service
Home-page: https://github.com/akrog/cinderlib-csi
Author: Gorka Eguileor
Author-email: gorka@eguileor.com
License: Apache Software License 2.0
Keywords: cinderlib_csi
Platform: UNKNOWN
Classifier: Development Status :: 2 - Pre-Alpha
Classifier: Intended Audience :: Developers
Classifier: License :: OSI Approved :: Apache Software License
Classifier: Natural Language :: English
Classifier: Programming Language :: Python :: 2
Classifier: Programming Language :: Python :: 2.7
Requires-Dist: cinderlib (>=0.2.1)
Requires-Dist: grpcio (==1.12.0)
Requires-Dist: protobuf (>=3.5.0.post1)
